dircontextgen/__init__.py
dircontextgen/cli.py
dircontextgen/core.py
dircontextgen/utils/__init__.py
dircontextgen/utils/file_handling.py
dircontextgen/utils/ignore_patterns.py
dircontextgen/utils/tree_generation.py
tests/__init__.py
tests/conftest.py
tests/test_core.py
tests/test_utils.py
dircontextgen-0.1.0.dist-info/LICENSE
dircontextgen-0.1.0.dist-info/METADATA
dircontextgen-0.1.0.dist-info/WHEEL
dircontextgen-0.1.0.dist-info/entry_points.txt
dircontextgen-0.1.0.dist-info/top_level.txt
dircontextgen-0.1.0.dist-info/RECORD
