Metadata-Version: 2.2
Name: dircontextgen
Version: 0.1.0
Summary: Generate context documentation from directory contents with advanced filtering
Author-email: Mithran Mohanraj <mithran.mohanraj@gmail.com>
Requires-Python: >=3.7
License-File: LICENSE
Requires-Dist: click>=8.0.0
Provides-Extra: dev
Requires-Dist: pytest>=8.0.0; extra == "dev"
Requires-Dist: pytest-cov>=4.1.0; extra == "dev"
Requires-Dist: build>=1.0.0; extra == "dev"
Requires-Dist: twine>=4.0.0; extra == "dev"
Requires-Dist: pylint>=3.0.0; extra == "dev"
Requires-Dist: black>=24.0.0; extra == "dev"
Requires-Dist: mypy>=1.8.0; extra == "dev"
